LICENSE
craigslistscraper/__init__.py
craigslistscraper/ad.py
craigslistscraper/data/areas.json
craigslistscraper/data/categories.json
craigslistscraper/data/us_cities.csv
craigslistscraper/search.py
craigslistscraper/utils.py
craigslistscraper-1.1.2.dist-info/LICENSE
craigslistscraper-1.1.2.dist-info/METADATA
craigslistscraper-1.1.2.dist-info/WHEEL
craigslistscraper-1.1.2.dist-info/RECORD
