Metadata-Version: 2.1
Name: craigslistscraper
Version: 1.1.2
Summary: Simple webscraper for Craigslist.
Home-page: https://github.com/ryanirl/craigslistscraper
License: MIT
Author: Ryan Peters
Author-email: RyanIRL@icloud.com
Requires-Python: >=3.7,<4.0
Classifier: Intended Audience :: Developers
Classifier: License :: OSI Approved :: MIT License
Classifier: Programming Language :: Python :: 3
Classifier: Programming Language :: Python :: 3.7
Classifier: Programming Language :: Python :: 3.8
Classifier: Programming Language :: Python :: 3.9
Classifier: Programming Language :: Python :: 3.10
Classifier: Programming Language :: Python :: 3.11
Classifier: Programming Language :: Python :: 3 :: Only
Requires-Dist: beautifulsoup4
Requires-Dist: requests
Project-URL: Repository, https://github.com/ryanirl/craigslistscraper
